pyopenproject/__init__.py
pyopenproject/openproject.py
pyopenproject/api_connection/__init__.py
pyopenproject/api_connection/command.py
pyopenproject/api_connection/request.py
pyopenproject/api_connection/exceptions/__init__.py
pyopenproject/api_connection/exceptions/request_exception.py
pyopenproject/api_connection/requests/__init__.py
pyopenproject/api_connection/requests/delete_request.py
pyopenproject/api_connection/requests/get_request.py
pyopenproject/api_connection/requests/patch_request.py
pyopenproject/api_connection/requests/post_request.py
pyopenproject/api_connection/requests/put_request.py
pyopenproject/business/__init__.py
pyopenproject/business/abstract_service.py
pyopenproject/business/activity_service.py
pyopenproject/business/attachment_service.py
pyopenproject/business/budget_service.py
pyopenproject/business/category_service.py
pyopenproject/business/configuration_service.py
pyopenproject/business/custom_action_service.py
pyopenproject/business/custom_object_service.py
pyopenproject/business/document_service.py
pyopenproject/business/grid_service.py
pyopenproject/business/group_service.py
pyopenproject/business/help_texts_service.py
pyopenproject/business/membership_service.py
pyopenproject/business/news_service.py
pyopenproject/business/post_service.py
pyopenproject/business/previewing_service.py
pyopenproject/business/principal_service.py
pyopenproject/business/priority_service.py
pyopenproject/business/project_service.py
pyopenproject/business/query_service.py
pyopenproject/business/relation_service.py
pyopenproject/business/revision_service.py
pyopenproject/business/role_service.py
pyopenproject/business/root_service.py
pyopenproject/business/schema_service.py
pyopenproject/business/status_service.py
pyopenproject/business/time_entry_service.py
pyopenproject/business/type_service.py
pyopenproject/business/user_preferences_service.py
pyopenproject/business/user_service.py
pyopenproject/business/version_service.py
pyopenproject-0.7.4.dist-info/LICENSE
pyopenproject-0.7.4.dist-info/METADATA
pyopenproject-0.7.4.dist-info/WHEEL
pyopenproject-0.7.4.dist-info/top_level.txt
pyopenproject-0.7.4.dist-info/RECORD
