Metadata-Version: 2.1
Name: pyopenproject
Version: 0.7.4
Summary: Python library to manage OpenProject API endpoints
Home-page: https://github.com/Flying-Free/python-openproject-api
Author: Alan Padierna Fernández
Author-email: alanpadierna9595@gmail.com
License: UNKNOWN
Platform: UNKNOWN
Classifier: Programming Language :: Python :: 3
Classifier: License :: OSI Approved :: MIT License
Classifier: Operating System :: OS Independent
Requires-Python: >=3.6
Requires-Dist: requests (~=2.25.1)
Requires-Dist: PyYAML (~=5.3.1)
Requires-Dist: python-dateutil (~=2.8.1)
Requires-Dist: isodate
